ashttp.py
ashttp-0.1.6.dist-info/LICENSE.md
ashttp-0.1.6.dist-info/METADATA
ashttp-0.1.6.dist-info/WHEEL
ashttp-0.1.6.dist-info/top_level.txt
ashttp-0.1.6.dist-info/RECORD
