Metadata-Version: 2.1
Name: ashttp
Version: 0.1.6
Summary: Super fast asynchronous HTTP client.
Home-page: https://github.com/gaojiuli/ashttp
Author: Jiuli Gao
Author-email: gaojiuli@gmail.com
License: MIT
Platform: UNKNOWN
Classifier: Development Status :: 5 - Production/Stable
Classifier: Intended Audience :: Developers
Classifier: License :: OSI Approved :: MIT License
Classifier: Programming Language :: Python :: 3.6
Classifier: Programming Language :: Python :: 3.7
Requires-Dist: cchardet
Requires-Dist: httptools
Requires-Dist: pyquery
